htmlmetadata/__init__.py
htmlmetadata/__main__.py
htmlmetadata/main.py
htmlmetadata/rules.py
htmlmetadata-1.1.dist-info/LICENSE
htmlmetadata-1.1.dist-info/METADATA
htmlmetadata-1.1.dist-info/WHEEL
htmlmetadata-1.1.dist-info/entry_points.txt
htmlmetadata-1.1.dist-info/top_level.txt
htmlmetadata-1.1.dist-info/RECORD
