Metadata-Version: 2.1
Name: htmlmetadata
Version: 1.1
Summary: Extract metadata from html pages using Open Graph metadata, HTML metadata, and a series of fallbacks
Home-page: https://github.com/mariocesar/htmlmetadata
Author: "M. César Señoranis"
Author-email: "mariocesar@humanzilla.com"
License: MIT License
Project-URL: Tracker, https://github.com/mariocesar/htmlmetadata/issues
Platform: UNKNOWN
Classifier: Intended Audience :: Developers
Classifier: License :: OSI Approved :: MIT License
Classifier: Operating System :: OS Independent
Classifier: Programming Language :: Python :: 3
Classifier: Programming Language :: Python :: 3.6
Classifier: Programming Language :: Python :: 3.7
Classifier: Programming Language :: Python :: 3.8
Requires-Python: >=3.6
Requires-Dist: beautifulsoup4 (>=4.8.1)
Requires-Dist: html5 (>=0.0.9)
Provides-Extra: develop
Requires-Dist: wheel ; extra == 'develop'
Requires-Dist: twine ; extra == 'develop'
Requires-Dist: flake8 ; extra == 'develop'
Requires-Dist: pytest ; extra == 'develop'
